toopher
