Metadata-Version: 1.1
Name: toopher
Version: 1.0.5
Summary: Wrapper library for the Toopher authentication API
Home-page: https://dev.toopher.com
Author: Toopher, Inc.
Author-email: support@toopher.com
License: UNKNOWN
Platform: UNKNOWN
Classifier: Development Status :: 5 - Production/Stable
Classifier: Intended Audience :: Developers
Classifier: License :: OSI Approved :: MIT License
Classifier: Operating System :: OS Independent
Classifier: Programming Language :: Python
Classifier: Topic :: Security
Classifier: Topic :: Software Development :: Libraries :: Python Modules
